__init__.py
data.py
isofits.py
module.py
test.py
isofits-1.0.dist-info/LICENSE
isofits-1.0.dist-info/METADATA
isofits-1.0.dist-info/WHEEL
isofits-1.0.dist-info/top_level.txt
isofits-1.0.dist-info/RECORD
