Metadata-Version: 2.1
Name: isofits
Version: 1.0
Summary: A package for calculating iso hole/shaft tolerances
Author-email: Parker Greene <parkergreene16@gmail.com>
Project-URL: Homepage, https://github.com/pgreene16/isofits
Project-URL: Issues, https://github.com/pgreene16/isofits/issues
Classifier: Programming Language :: Python :: 3
Classifier: License :: OSI Approved :: MIT License
Classifier: Operating System :: OS Independent
Requires-Python: >=3.8
License-File: LICENSE
